{
    "Objects": [
        {
            "name": "Land_Ruin_HouseSmall1_Half",
            "pos": [
                13415.83984375,
                13.445876121520996,
                4014.709228515625
            ],
            "ypr": [
                156.99984741210938,
                0.0,
                0.0
            ]
        },
        {
            "name": "Land_Ruin_HouseSmall2_NoIvy",
            "pos": [
                13416.5888671875,
                13.626493453979493,
                4012.888671875
            ],
            "ypr": [
                60.999847412109378,
                -4.999985694885254,
                -11.999984741210938
            ]
        },
        {
            "name": "CraterLong",
            "pos": [
                13422.912109375,
                11.804848670959473,
                4005.45166015625
            ],
            "ypr": [
                45.999908447265628,
                17.99998664855957,
                15.999995231628418
            ]
        },
        {
            "name": "CraterLong",
            "pos": [
                13418.033203125,
                14.280660629272461,
                4019.17529296875
            ],
            "ypr": [
                -64.99982452392578,
                4.999998092651367,
                -4.999990940093994
            ]
        },
        {
            "name": "CraterLong",
            "pos": [
                13411.0146484375,
                14.191961288452149,
                4018.043212890625
            ],
            "ypr": [
                60.999820709228519,
                0.0,
                14.999991416931153
            ]
        },
        {
            "name": "Land_Ruin_Camp_House",
            "pos": [
                13407.5517578125,
                14.933205604553223,
                4013.929443359375
            ],
            "ypr": [
                0.0,
                0.0,
                0.0
            ]
        },
        {
            "name": "Land_Ruin_HouseBig2_Half",
            "pos": [
                13379.2275390625,
                11.902444839477539,
                3942.864013671875
            ],
            "ypr": [
                -23.999971389770509,
                0.0,
                0.0
            ]
        },
        {
            "name": "Land_Ruin_HouseBig1_NoIvy_Half",
            "pos": [
                13546.044921875,
                10.173490524291993,
                3964.142578125
            ],
            "ypr": [
                -41.99993896484375,
                0.0,
                0.0
            ]
        },
        {
            "name": "Land_Ruin_HouseBig1_NoIvy",
            "pos": [
                13544.9189453125,
                6.849998950958252,
                3966.995849609375
            ],
            "ypr": [
                84.99998474121094,
                -26.999927520751954,
                12.999946594238282
            ]
        },
        {
            "name": "Land_Ruin_Church2",
            "pos": [
                13495.7998046875,
                11.484872817993164,
                3975.406982421875
            ],
            "ypr": [
                -78.99974822998047,
                0.0,
                0.0
            ]
        },
        {
            "name": "Land_Ruin_Church2",
            "pos": [
                13503.6396484375,
                6.0,
                3972.55078125
            ],
            "ypr": [
                71.99978637695313,
                24.999980926513673,
                -9.999987602233887
            ]
        },
        {
            "name": "Land_Church4_Red",
            "pos": [
                13491.98046875,
                4.249992847442627,
                3957.66015625
            ],
            "ypr": [
                69.99978637695313,
                32.99994659423828,
                12.99996280670166
            ]
        },
        {
            "name": "Land_Ruin_House_1W03",
            "pos": [
                13501.7373046875,
                6.359875202178955,
                3960.11767578125
            ],
            "ypr": [
                48.99988555908203,
                4.999998092651367,
                8.999994277954102
            ]
        },
        {
            "name": "CraterLong",
            "pos": [
                13494.8681640625,
                6.000102996826172,
                3962.264404296875
            ],
            "ypr": [
                31.999971389770509,
                3.0,
                0.9999949336051941
            ]
        },
        {
            "name": "Land_Ruin_Chapel2_White",
            "pos": [
                13494.314453125,
                6.585774898529053,
                3956.005859375
            ],
            "ypr": [
                9.999996185302735,
                -3.0,
                -0.9999998211860657
            ]
        },
        {
            "name": "Land_House_1W13_Dam",
            "pos": [
                13631.9814453125,
                23.29495620727539,
                3913.8681640625
            ],
            "ypr": [
                128.99940490722657,
                0.0,
                0.0
            ]
        },
        {
            "name": "Land_Misc_Greenhouse",
            "pos": [
                13627.50390625,
                22.743667602539064,
                3928.258056640625
            ],
            "ypr": [
                -179.99996948242188,
                0.0,
                0.0
            ]
        },
        {
            "name": "Land_Shed_W1",
            "pos": [
                13625.5009765625,
                22.60559844970703,
                3921.23828125
            ],
            "ypr": [
                -59.999855041503909,
                0.0,
                0.0
            ]
        },
        {
            "name": "Land_misc_chickenCoop",
            "pos": [
                13622.5419921875,
                21.678163528442384,
                3929.16015625
            ],
            "ypr": [
                62.99983596801758,
                0.0,
                0.0
            ]
        },
        {
            "name": "Land_Misc_Toilet_Dry",
            "pos": [
                13624.302734375,
                22.213211059570314,
                3910.90380859375
            ],
            "ypr": [
                64.99974060058594,
                0.0,
                0.0
            ]
        },
        {
            "name": "Land_Wreck_S1023_Blue",
            "pos": [
                13632.466796875,
                20.805267333984376,
                3961.535888671875
            ],
            "ypr": [
                0.0,
                -0.9999999403953552,
                5.999996185302734
            ]
        },
        {
            "name": "Land_Wreck_Lada_Green",
            "pos": [
                13629.87890625,
                20.088233947753908,
                3964.946533203125
            ],
            "ypr": [
                9.999996185302735,
                -3.0,
                6.999998092651367
            ]
        },
        {
            "name": "Land_Wreck_Volha_Blue",
            "pos": [
                13629.5732421875,
                20.860387802124025,
                3957.353515625
            ],
            "ypr": [
                -1.9999998807907105,
                0.9999999403953552,
                2.9999969005584719
            ]
        },
        {
            "name": "Land_Wreck_Tractor",
            "pos": [
                13635.3330078125,
                21.722501754760743,
                3951.125
            ],
            "ypr": [
                -149.9998321533203,
                4.999989986419678,
                -1.9999998807907105
            ]
        },
        {
            "name": "Land_Chapel",
            "pos": [
                13602.1689453125,
                23.51340675354004,
                3971.77392578125
            ],
            "ypr": [
                34.99996566772461,
                0.0,
                0.0
            ]
        },
        {
            "name": "Land_Roadblock_WoodenCrate",
            "pos": [
                13603.7998046875,
                19.47296714782715,
                3973.372802734375
            ],
            "ypr": [
                -5.999996185302734,
                -2.0,
                1.9999992847442628
            ]
        },
        {
            "name": "Land_Castle_WallS_End",
            "pos": [
                13626.40625,
                20.532764434814454,
                3948.2734375
            ],
            "ypr": [
                -114.9999008178711,
                -7.999997138977051,
                40.99993896484375
            ]
        },
        {
            "name": "Land_Castle_WallS_5_D",
            "pos": [
                13630.0556640625,
                21.069108963012697,
                3932.91796875
            ],
            "ypr": [
                -76.9992904663086,
                -8.999977111816407,
                -2.9999887943267824
            ]
        },
        {
            "name": "Land_Castle_WallS_10",
            "pos": [
                13629.0546875,
                21.6835880279541,
                3941.756103515625
            ],
            "ypr": [
                -104.99959564208985,
                0.0,
                3.999999761581421
            ]
        },
        {
            "name": "Land_Roadblock_WoodenCrate",
            "pos": [
                13629.7421875,
                21.989246368408204,
                3911.09521484375
            ],
            "ypr": [
                -48.99980545043945,
                0.0,
                0.0
            ]
        },
        {
            "name": "Land_House_1W05",
            "pos": [
                13600.1806640625,
                20.42131996154785,
                4042.016357421875
            ],
            "ypr": [
                169.99978637695313,
                0.0,
                0.0
            ]
        },
        {
            "name": "Land_Shed_W6",
            "pos": [
                13577.82421875,
                20.95672607421875,
                4056.724853515625
            ],
            "ypr": [
                -54.9990348815918,
                0.0,
                0.0
            ]
        },
        {
            "name": "Land_House_1W08",
            "pos": [
                13660.5263671875,
                11.179367065429688,
                4049.351318359375
            ],
            "ypr": [
                -39.99993896484375,
                0.0,
                0.0
            ]
        },
        {
            "name": "Land_Shed_M1",
            "pos": [
                13647.1416015625,
                11.770776748657227,
                4062.726806640625
            ],
            "ypr": [
                -37.99995422363281,
                0.0,
                0.0
            ]
        },
        {
            "name": "Land_Misc_Polytunnel",
            "pos": [
                13642.6513671875,
                12.436365127563477,
                4065.023193359375
            ],
            "ypr": [
                -72.99874114990235,
                0.0,
                0.0
            ]
        },
        {
            "name": "Land_Misc_Toilet_Dry",
            "pos": [
                13654.123046875,
                12.749484062194825,
                4068.94384765625
            ],
            "ypr": [
                -159.99993896484376,
                0.0,
                0.0
            ]
        },
        {
            "name": "Land_Misc_DeerStand2",
            "pos": [
                13610.21484375,
                12.434816360473633,
                4124.89013671875
            ],
            "ypr": [
                137.9993438720703,
                0.0,
                0.0
            ]
        },
        {
            "name": "Land_Farm_Hopper",
            "pos": [
                13578.224609375,
                25.35848617553711,
                4062.342041015625
            ],
            "ypr": [
                -54.999874114990237,
                0.0,
                0.0
            ]
        },
        {
            "name": "Land_Wreck_Uaz",
            "pos": [
                13583.6552734375,
                19.46384620666504,
                4060.373779296875
            ],
            "ypr": [
                -67.99980926513672,
                1.9999979734420777,
                5.999996662139893
            ]
        },
        {
            "name": "Land_Castle_WallS_5_D",
            "pos": [
                13501.64453125,
                4.115441799163818,
                4322.43212890625
            ],
            "ypr": [
                -24.999969482421876,
                8.999993324279786,
                0.0
            ]
        },
        {
            "name": "Land_Castle_WallS_10",
            "pos": [
                13509.8662109375,
                2.8133111000061037,
                4328.2822265625
            ],
            "ypr": [
                -44.999916076660159,
                -18.999980926513673,
                30.99997329711914
            ]
        },
        {
            "name": "Land_Castle_WallS_10",
            "pos": [
                13512.400390625,
                2.243025064468384,
                4337.0361328125
            ],
            "ypr": [
                100.99959564208985,
                0.0,
                -34.99996566772461
            ]
        },
        {
            "name": "Land_Castle_WallS_10",
            "pos": [
                13465.2880859375,
                6.099747180938721,
                4292.40087890625
            ],
            "ypr": [
                86.99970245361328,
                0.0,
                0.0
            ]
        },
        {
            "name": "Land_Castle_WallS_5_D",
            "pos": [
                13467.3623046875,
                5.42494010925293,
                4283.82568359375
            ],
            "ypr": [
                67.99980926513672,
                0.0,
                0.0
            ]
        },
        {
            "name": "Land_Castle_WallS_10",
            "pos": [
                13465.5546875,
                3.6859209537506105,
                4298.9541015625
            ],
            "ypr": [
                -64.99982452392578,
                0.0,
                -36.99992752075195
            ]
        },
        {
            "name": "Land_Guardhouse",
            "pos": [
                13480.5048828125,
                6.299781799316406,
                4321.8740234375
            ],
            "ypr": [
                19.99998664855957,
                0.0,
                0.0
            ]
        },
        {
            "name": "Land_Mil_GuardBox_Green",
            "pos": [
                13474.916015625,
                6.603933811187744,
                4310.99267578125
            ],
            "ypr": [
                109.99951171875,
                0.0,
                0.0
            ]
        },
        {
            "name": "Land_Wall_Gate_Ind3",
            "pos": [
                13474.8642578125,
                6.429082870483398,
                4317.19921875
            ],
            "ypr": [
                -68.99980163574219,
                0.0,
                0.0
            ]
        },
        {
            "name": "Land_Castle_WallS_End",
            "pos": [
                13470.572265625,
                5.931294918060303,
                4309.419921875
            ],
            "ypr": [
                -50.999874114990237,
                0.0,
                0.0
            ]
        },
        {
            "name": "Land_Castle_WallS_5_D",
            "pos": [
                13469.00390625,
                5.433438777923584,
                4305.94091796875
            ],
            "ypr": [
                -57.999839782714847,
                0.0,
                0.0
            ]
        },
        {
            "name": "Land_Castle_WallS_10",
            "pos": [
                13492.27734375,
                3.706820011138916,
                4319.03369140625
            ],
            "ypr": [
                -4.999989986419678,
                0.0,
                29.999971389770509
            ]
        },
        {
            "name": "Land_Castle_Wall1_20",
            "pos": [
                13481.4853515625,
                0.0,
                4334.47509765625
            ],
            "ypr": [
                -76.9997329711914,
                0.0,
                0.0
            ]
        },
        {
            "name": "Land_Castle_Wall1_20",
            "pos": [
                13486.0107421875,
                0.0,
                4354.03466796875
            ],
            "ypr": [
                -77.0,
                0.0,
                0.0
            ]
        },
        {
            "name": "Land_Castle_Wall1_20",
            "pos": [
                13490.0966796875,
                0.0,
                4371.86279296875
            ],
            "ypr": [
                -77.0,
                0.0,
                0.0
            ]
        },
        {
            "name": "Land_Castle_Wall1_20_Turn",
            "pos": [
                13496.2587890625,
                0.0,
                4390.29296875
            ],
            "ypr": [
                -57.999813079833987,
                0.0,
                0.0
            ]
        },
        {
            "name": "Land_Castle_Wall1_20",
            "pos": [
                13506.41796875,
                0.0,
                4407.15478515625
            ],
            "ypr": [
                -52.99989318847656,
                0.0,
                0.0
            ]
        },
        {
            "name": "Land_Castle_Wall1_20",
            "pos": [
                13534.859375,
                0.0,
                4442.27294921875
            ],
            "ypr": [
                -48.99988555908203,
                0.0,
                0.0
            ]
        },
        {
            "name": "Land_Castle_Wall1_End1",
            "pos": [
                13523.630859375,
                0.0,
                4428.65625
            ],
            "ypr": [
                -51.999900817871097,
                0.0,
                0.0
            ]
        },
        {
            "name": "Land_Castle_Wall1_End2",
            "pos": [
                13517.7490234375,
                0.0,
                4421.94189453125
            ],
            "ypr": [
                -51.99981689453125,
                0.0,
                0.0
            ]
        },
        {
            "name": "Land_Castle_Wall1_End2",
            "pos": [
                13547.0341796875,
                0.0,
                4455.1474609375
            ],
            "ypr": [
                -43.999916076660159,
                0.0,
                0.0
            ]
        },
        {
            "name": "Land_Castle_Wall1_End2",
            "pos": [
                13549.6943359375,
                2.573991060256958,
                4458.55419921875
            ],
            "ypr": [
                -47.99989318847656,
                0.0,
                -31.999956130981447
            ]
        },
        {
            "name": "Land_Castle_Wall2_End2",
            "pos": [
                13560.0908203125,
                -0.24223199486732484,
                4473.9677734375
            ],
            "ypr": [
                110.99956512451172,
                0.0,
                -44.999752044677737
            ]
        },
        {
            "name": "Land_Boathouse",
            "pos": [
                13579.8369140625,
                -1.3137010335922242,
                4278.30224609375
            ],
            "ypr": [
                -87.99969482421875,
                0.0,
                0.0
            ]
        },
        {
            "name": "Land_Castle_Stairs",
            "pos": [
                13571.396484375,
                -4.980000019073486,
                4267.44140625
            ],
            "ypr": [
                0.0,
                0.0,
                0.0
            ]
        },
        {
            "name": "Land_Boat_Small1",
            "pos": [
                13577.0986328125,
                0.7402690052986145,
                4280.4638671875
            ],
            "ypr": [
                11.999992370605469,
                3.9999988079071047,
                6.999996185302734
            ]
        },
        {
            "name": "Land_House_1W10_Brown",
            "pos": [
                13558.59375,
                10.360276222229004,
                4180.86083984375
            ],
            "ypr": [
                0.0,
                0.0,
                0.0
            ]
        },
        {
            "name": "Land_Shed_W2",
            "pos": [
                13573.3544921875,
                10.034767150878907,
                4195.12353515625
            ],
            "ypr": [
                -25.999980926513673,
                0.0,
                0.0
            ]
        },
        {
            "name": "Land_Misc_Greenhouse",
            "pos": [
                13533.904296875,
                8.189927101135254,
                4179.3798828125
            ],
            "ypr": [
                148.99923706054688,
                0.0,
                0.0
            ]
        },
        {
            "name": "Land_Wreck_Caravan_MRust",
            "pos": [
                13540.36328125,
                9.477497100830079,
                4169.29736328125
            ],
            "ypr": [
                -146.99920654296876,
                0.0,
                0.0
            ]
        },
        {
            "name": "Land_misc_chickenCoop",
            "pos": [
                13532.052734375,
                6.8482890129089359,
                4183.44970703125
            ],
            "ypr": [
                -175.99945068359376,
                0.0,
                0.0
            ]
        },
        {
            "name": "Land_Wreck_Lada_Green",
            "pos": [
                13538.1064453125,
                8.262683868408204,
                4172.59765625
            ],
            "ypr": [
                48.999916076660159,
                3.0,
                -4.999998092651367
            ]
        },
        {
            "name": "Land_Wreck_S1023_Blue",
            "pos": [
                13569.21875,
                10.59807014465332,
                4184.5947265625
            ],
            "ypr": [
                -17.999990463256837,
                -1.9999992847442628,
                -12.999996185302735
            ]
        },
        {
            "name": "Land_House_1W01",
            "pos": [
                13496.37109375,
                6.767571926116943,
                4224.84423828125
            ],
            "ypr": [
                -88.9991683959961,
                0.0,
                0.0
            ]
        },
        {
            "name": "Land_Shed_M3",
            "pos": [
                13496.5615234375,
                4.6967010498046879,
                4205.26171875
            ],
            "ypr": [
                -32.99997329711914,
                0.0,
                0.0
            ]
        },
        {
            "name": "Land_Shed_M4",
            "pos": [
                13476.486328125,
                6.084670066833496,
                4243.69482421875
            ],
            "ypr": [
                -74.99964141845703,
                0.0,
                0.0
            ]
        },
        {
            "name": "Land_Wreck_Volha_Grey",
            "pos": [
                13495.9033203125,
                4.063739776611328,
                4233.9921875
            ],
            "ypr": [
                71.99978637695313,
                -5.9999918937683109,
                -8.999993324279786
            ]
        },
        {
            "name": "Land_House_1W11",
            "pos": [
                13494.0556640625,
                7.307602882385254,
                4243.916015625
            ],
            "ypr": [
                0.0,
                0.0,
                0.0
            ]
        },
        {
            "name": "Land_Castle_Stairs_nolc",
            "pos": [
                13500.490234375,
                -2.4999990463256838,
                4241.2001953125
            ],
            "ypr": [
                -89.99998474121094,
                0.0,
                0.0
            ]
        },
        {
            "name": "Land_Wreck_hb01_aban1_blue",
            "pos": [
                13500.9892578125,
                4.093198776245117,
                4210.3251953125
            ],
            "ypr": [
                55.9998779296875,
                -3.0,
                0.0
            ]
        },
        {
            "name": "Land_Wreck_hb01_aban2_blue",
            "pos": [
                13503.755859375,
                3.7553250789642336,
                4213.82470703125
            ],
            "ypr": [
                80.9997329711914,
                -1.9999990463256837,
                2.0
            ]
        },
        {
            "name": "Land_HouseBlock_2F4",
            "pos": [
                13534.5400390625,
                12.050000190734864,
                4310.8798828125
            ],
            "ypr": [
                -82.0,
                0.0,
                0.0
            ]
        },
        {
            "name": "Land_HouseBlock_2F8",
            "pos": [
                13536.400390625,
                11.501996040344239,
                4327.09375
            ],
            "ypr": [
                -82.0,
                0.0,
                0.0
            ]
        },
        {
            "name": "Land_HouseBlock_2F7",
            "pos": [
                13541.44140625,
                11.536870956420899,
                4346.94775390625
            ],
            "ypr": [
                -82.0,
                0.0,
                0.0
            ]
        },
        {
            "name": "Land_HouseBlock_2F9",
            "pos": [
                13561.533203125,
                10.854331016540528,
                4425.37939453125
            ],
            "ypr": [
                134.99908447265626,
                0.0,
                0.0
            ]
        },
        {
            "name": "Land_HouseBlock_2F8",
            "pos": [
                13547.5458984375,
                10.685876846313477,
                4411.1611328125
            ],
            "ypr": [
                135.0,
                0.0,
                0.0
            ]
        },
        {
            "name": "Land_Village_Pub",
            "pos": [
                13526.8251953125,
                9.328446388244629,
                4468.07568359375
            ],
            "ypr": [
                53.9998893737793,
                0.0,
                0.0
            ]
        },
        {
            "name": "Land_Misc_TrailRoof_Small",
            "pos": [
                13471.8623046875,
                7.45696496963501,
                4471.67724609375
            ],
            "ypr": [
                -53.999839782714847,
                0.0,
                0.0
            ]
        },
        {
            "name": "Land_Misc_TrailRoof_Small",
            "pos": [
                13470.751953125,
                7.4437761306762699,
                4463.5244140625
            ],
            "ypr": [
                75.99976348876953,
                0.0,
                0.0
            ]
        },
        {
            "name": "Land_BusStop_Village2",
            "pos": [
                13479.359375,
                7.122066974639893,
                4496.64306640625
            ],
            "ypr": [
                -80.99971008300781,
                0.0,
                0.0
            ]
        },
        {
            "name": "Land_FuelStation_Build",
            "pos": [
                13503.541015625,
                7.622334003448486,
                4417.01904296875
            ],
            "ypr": [
                131.99911499023438,
                0.0,
                0.0
            ]
        },
        {
            "name": "Land_FuelStation_Feed",
            "pos": [
                13502.45703125,
                6.733398914337158,
                4420.4833984375
            ],
            "ypr": [
                -45.99992370605469,
                0.0,
                0.0
            ]
        },
        {
            "name": "Land_City_Stand_News2",
            "pos": [
                13500.4775390625,
                7.365266799926758,
                4407.21875
            ],
            "ypr": [
                133.999267578125,
                0.0,
                0.0
            ]
        },
        {
            "name": "Land_City_Stand_News1",
            "pos": [
                13498.4130859375,
                7.255099773406982,
                4402.61083984375
            ],
            "ypr": [
                117.99933624267578,
                0.0,
                0.0
            ]
        },
        {
            "name": "Land_City_Stand_FastFood",
            "pos": [
                13490.4130859375,
                7.644475936889648,
                4395.05859375
            ],
            "ypr": [
                159.99993896484376,
                0.0,
                0.0
            ]
        },
        {
            "name": "Land_Shed_W5",
            "pos": [
                13534.4404296875,
                5.9392008781433109,
                4451.64453125
            ],
            "ypr": [
                43.999916076660159,
                0.0,
                0.0
            ]
        },
        {
            "name": "Land_Shed_W6",
            "pos": [
                13546.28515625,
                5.282074928283691,
                4477.7080078125
            ],
            "ypr": [
                107.99958038330078,
                0.0,
                0.0
            ]
        },
        {
            "name": "Land_Wreck_Uaz",
            "pos": [
                13503.029296875,
                6.9193878173828129,
                4475.1748046875
            ],
            "ypr": [
                8.999994277954102,
                0.0,
                0.0
            ]
        },
        {
            "name": "Land_Wreck_Ikarus",
            "pos": [
                13483.2431640625,
                7.495242118835449,
                4482.10693359375
            ],
            "ypr": [
                3.999999761581421,
                -1.9999992847442628,
                -5.999996185302734
            ]
        },
        {
            "name": "Land_Wreck_Ikarus",
            "pos": [
                13484.8876953125,
                7.371278762817383,
                4506.341796875
            ],
            "ypr": [
                12.999996185302735,
                -0.9999999403953552,
                -4.999998092651367
            ]
        },
        {
            "name": "Land_Wreck_S1023_Beige",
            "pos": [
                13490.1484375,
                7.079133987426758,
                4510.55859375
            ],
            "ypr": [
                -3.0,
                0.0,
                0.0
            ]
        },
        {
            "name": "Land_Wreck_Volha_Blue",
            "pos": [
                13488.390625,
                6.816943168640137,
                4519.11767578125
            ],
            "ypr": [
                -12.999996185302735,
                0.0,
                3.0
            ]
        },
        {
            "name": "Land_Wreck_hb01_aban1_white",
            "pos": [
                13491.76171875,
                7.141991138458252,
                4516.1396484375
            ],
            "ypr": [
                -3.0,
                0.0,
                0.0
            ]
        },
        {
            "name": "Land_Wreck_hb02_aban1_red",
            "pos": [
                13490.78515625,
                6.8552632331848148,
                4528.28857421875
            ],
            "ypr": [
                14.999991416931153,
                0.0,
                0.0
            ]
        },
        {
            "name": "Land_Wreck_Lada_Green",
            "pos": [
                13492.1298828125,
                6.744694232940674,
                4523.69775390625
            ],
            "ypr": [
                5.999996185302734,
                0.0,
                0.0
            ]
        },
        {
            "name": "Land_Wreck_Uaz",
            "pos": [
                13493.818359375,
                6.943185806274414,
                4531.9453125
            ],
            "ypr": [
                -4.999998092651367,
                0.0,
                0.0
            ]
        },
        {
            "name": "Land_Wreck_Volha_Grey",
            "pos": [
                13493.2705078125,
                6.83694314956665,
                4537.33056640625
            ],
            "ypr": [
                0.0,
                0.0,
                0.0
            ]
        },
        {
            "name": "Land_Wreck_V3S",
            "pos": [
                13490.240234375,
                7.4857048988342289,
                4418.2138671875
            ],
            "ypr": [
                -161.99969482421876,
                -1.9999990463256837,
                -3.0
            ]
        },
        {
            "name": "Land_Wreck_S1023_Blue",
            "pos": [
                13476.822265625,
                7.209134101867676,
                4462.09033203125
            ],
            "ypr": [
                -18.999988555908204,
                0.0,
                0.0
            ]
        },
        {
            "name": "Land_Wreck_Lada_Green",
            "pos": [
                13477.658203125,
                6.821496963500977,
                4455.3359375
            ],
            "ypr": [
                1.9999998807907105,
                0.0,
                0.0
            ]
        },
        {
            "name": "Land_Wreck_hb01_aban2_green",
            "pos": [
                13501.572265625,
                7.124415874481201,
                4467.248046875
            ],
            "ypr": [
                -169.99990844726563,
                0.0,
                0.0
            ]
        },
        {
            "name": "Land_Wreck_hb02_aban2_black",
            "pos": [
                13493.1337890625,
                6.9092698097229,
                4451.65966796875
            ],
            "ypr": [
                -164.9998016357422,
                0.0,
                0.0
            ]
        },
        {
            "name": "Land_Wreck_sed01_aban1_black",
            "pos": [
                13495.0126953125,
                6.880380153656006,
                4424.306640625
            ],
            "ypr": [
                20.99998664855957,
                0.0,
                0.0
            ]
        },
        {
            "name": "Land_Wreck_Ikarus",
            "pos": [
                13489.06640625,
                7.505505084991455,
                4434.7939453125
            ],
            "ypr": [
                -169.99964904785157,
                -0.9999989867210388,
                -5.9999918937683109
            ]
        },
        {
            "name": "Land_Wreck_sed02_aban1_grey",
            "pos": [
                13489.7890625,
                7.056777000427246,
                4444.5419921875
            ],
            "ypr": [
                -169.99978637695313,
                0.0,
                0.0
            ]
        },
        {
            "name": "Land_wreck_truck01_aban2_blue",
            "pos": [
                13485.2626953125,
                6.112829208374023,
                4423.87158203125
            ],
            "ypr": [
                -169.99990844726563,
                0.0,
                0.0
            ]
        },
        {
            "name": "Land_Wreck_hb01_aban2_blue",
            "pos": [
                13485.2685546875,
                6.854931831359863,
                4395.83349609375
            ],
            "ypr": [
                -24.999963760375978,
                0.0,
                0.0
            ]
        },
        {
            "name": "Land_Wreck_Lada_Red",
            "pos": [
                13484.1103515625,
                6.659400939941406,
                4411.28076171875
            ],
            "ypr": [
                -159.9998016357422,
                0.0,
                0.0
            ]
        },
        {
            "name": "Land_Wreck_S1023_Blue",
            "pos": [
                13478.0146484375,
                6.724180221557617,
                4383.65087890625
            ],
            "ypr": [
                -167.99989318847657,
                0.0,
                0.0
            ]
        },
        {
            "name": "Land_Wreck_Volha_Grey",
            "pos": [
                13514.373046875,
                4.619316101074219,
                4335.3466796875
            ],
            "ypr": [
                3.9999988079071047,
                0.0,
                3.0
            ]
        },
        {
            "name": "Land_House_1W04",
            "pos": [
                13224.1845703125,
                8.52889347076416,
                4037.046142578125
            ],
            "ypr": [
                47.99992752075195,
                0.0,
                0.0
            ]
        },
        {
            "name": "Land_House_1W07",
            "pos": [
                13223.1103515625,
                8.506128311157227,
                4000.589599609375
            ],
            "ypr": [
                -41.99990463256836,
                0.0,
                0.0
            ]
        },
        {
            "name": "Land_Shed_W5",
            "pos": [
                13209.814453125,
                7.06144380569458,
                4006.133544921875
            ],
            "ypr": [
                137.9993133544922,
                0.0,
                0.0
            ]
        },
        {
            "name": "Land_Shed_Closed",
            "pos": [
                13288.4208984375,
                10.703781127929688,
                4100.4091796875
            ],
            "ypr": [
                46.99992752075195,
                0.0,
                0.0
            ]
        },
        {
            "name": "Land_Garage_Row_Small",
            "pos": [
                13255.2939453125,
                7.634291172027588,
                4075.389892578125
            ],
            "ypr": [
                121.99923706054688,
                0.0,
                0.0
            ]
        },
        {
            "name": "Land_HouseBlock_3F1",
            "pos": [
                13183.7744140625,
                13.910451889038086,
                3986.737548828125
            ],
            "ypr": [
                -39.999996185302737,
                0.0,
                0.0
            ]
        },
        {
            "name": "Land_HouseBlock_3F2",
            "pos": [
                13173.2783203125,
                13.779569625854493,
                3977.822021484375
            ],
            "ypr": [
                -39.999996185302737,
                0.0,
                0.0
            ]
        },
        {
            "name": "Land_HouseBlock_3F1",
            "pos": [
                13161.7314453125,
                13.651067733764649,
                3968.510009765625
            ],
            "ypr": [
                139.99998474121095,
                0.0,
                0.0
            ]
        },
        {
            "name": "Land_House_2B01",
            "pos": [
                13257.6953125,
                9.883209228515625,
                4042.8203125
            ],
            "ypr": [
                -135.0,
                0.0,
                0.0
            ]
        },
        {
            "name": "Land_Lamp_City1_amp",
            "pos": [
                13262.787109375,
                10.23248291015625,
                4080.9580078125
            ],
            "ypr": [
                -118.99952697753906,
                0.0,
                0.0
            ]
        },
        {
            "name": "PumpkinHelmet",
            "pos": [
                13262.1396484375,
                14.649998664855957,
                4079.561767578125
            ],
            "ypr": [
                148.43862915039063,
                -70.99996948242188,
                179.99989318847657
            ]
        },
        {
            "name": "Land_Shed_W2",
            "pos": [
                13193.544921875,
                6.006350040435791,
                4021.042724609375
            ],
            "ypr": [
                -179.99989318847657,
                0.0,
                0.0
            ]
        },
        {
            "name": "Land_Misc_Greenhouse",
            "pos": [
                13197.474609375,
                7.324179172515869,
                4014.748046875
            ],
            "ypr": [
                124.99947357177735,
                0.0,
                0.0
            ]
        },
        {
            "name": "Land_Misc_Toilet_Dry",
            "pos": [
                13220.6240234375,
                7.579217910766602,
                4044.979736328125
            ],
            "ypr": [
                155.9988555908203,
                0.0,
                0.0
            ]
        },
        {
            "name": "Land_Wreck_Uaz",
            "pos": [
                13208.619140625,
                6.803400039672852,
                4031.083251953125
            ],
            "ypr": [
                115.99954223632813,
                0.0,
                0.0
            ]
        },
        {
            "name": "Land_Wreck_Lada_Green",
            "pos": [
                13280.1806640625,
                6.473721027374268,
                4076.211669921875
            ],
            "ypr": [
                19.999990463256837,
                0.0,
                0.0
            ]
        },
        {
            "name": "Land_Wreck_S1023_Blue",
            "pos": [
                13281.185546875,
                7.258357048034668,
                4067.481201171875
            ],
            "ypr": [
                -97.99964141845703,
                0.0,
                0.0
            ]
        },
        {
            "name": "Land_Wreck_Volha_Grey",
            "pos": [
                13279.3818359375,
                6.837019920349121,
                4064.2529296875
            ],
            "ypr": [
                71.99978637695313,
                0.0,
                0.0
            ]
        },
        {
            "name": "Land_Wreck_hb01_aban1_green",
            "pos": [
                13280.9580078125,
                6.878330230712891,
                4081.573974609375
            ],
            "ypr": [
                11.999992370605469,
                0.0,
                1.9999998807907105
            ]
        },
        {
            "name": "Land_Wreck_hb02_aban1_red",
            "pos": [
                13247.595703125,
                6.718390941619873,
                4068.392822265625
            ],
            "ypr": [
                -53.9998893737793,
                0.0,
                0.0
            ]
        },
        {
            "name": "Land_Wreck_sed01_aban1_black",
            "pos": [
                13232.5859375,
                6.519999980926514,
                4038.414306640625
            ],
            "ypr": [
                -42.99992370605469,
                0.0,
                0.0
            ]
        },
        {
            "name": "Land_Wreck_sed02_aban1_red",
            "pos": [
                13232.640625,
                6.763113021850586,
                4044.628662109375
            ],
            "ypr": [
                143.99925231933595,
                0.0,
                0.0
            ]
        },
        {
            "name": "Land_wreck_truck01_aban1_orange",
            "pos": [
                13238.6982421875,
                5.199999809265137,
                3976.6171875
            ],
            "ypr": [
                45.99992370605469,
                0.0,
                0.0
            ]
        },
        {
            "name": "Land_Wreck_Tractor",
            "pos": [
                13271.6591796875,
                7.094281196594238,
                4088.8916015625
            ],
            "ypr": [
                48.99991989135742,
                0.0,
                0.0
            ]
        },
        {
            "name": "Land_Wreck_sed02_aban1_grey",
            "pos": [
                13188.0546875,
                6.055191993713379,
                3965.336669921875
            ],
            "ypr": [
                -5.999996185302734,
                0.0,
                0.0
            ]
        },
        {
            "name": "Land_Wreck_sed01_aban2_white",
            "pos": [
                13184.1484375,
                5.935409069061279,
                3962.28173828125
            ],
            "ypr": [
                174.99989318847657,
                0.0,
                0.0
            ]
        },
        {
            "name": "Land_Wreck_hb02_aban2_blue",
            "pos": [
                13180.767578125,
                5.874195098876953,
                3958.79638671875
            ],
            "ypr": [
                -5.999996185302734,
                0.0,
                0.0
            ]
        },
        {
            "name": "Land_Wreck_Volha_Blue",
            "pos": [
                13191.638671875,
                5.9383440017700199,
                3968.13525390625
            ],
            "ypr": [
                -4.999998092651367,
                0.0,
                0.0
            ]
        },
        {
            "name": "Land_Wreck_S1023_Blue",
            "pos": [
                13195.234375,
                6.199132919311523,
                3970.594482421875
            ],
            "ypr": [
                -3.0,
                0.0,
                0.0
            ]
        },
        {
            "name": "Land_Camp_House_white",
            "pos": [
                13031.25,
                7.820000171661377,
                3781.43212890625
            ],
            "ypr": [
                9.99999713897705,
                0.0,
                0.0
            ]
        },
        {
            "name": "Land_Camp_House_white",
            "pos": [
                13024.5771484375,
                7.820000171661377,
                3782.588623046875
            ],
            "ypr": [
                10.0,
                0.0,
                0.0
            ]
        },
        {
            "name": "Land_Camp_House_brown",
            "pos": [
                12989.98046875,
                7.774907112121582,
                3765.199462890625
            ],
            "ypr": [
                -39.999996185302737,
                0.0,
                0.0
            ]
        },
        {
            "name": "Land_Camp_House_brown",
            "pos": [
                12984.8154296875,
                7.717320919036865,
                3760.82080078125
            ],
            "ypr": [
                -39.999996185302737,
                0.0,
                0.0
            ]
        },
        {
            "name": "Land_Mil_Barracks6",
            "pos": [
                13055.6220703125,
                5.477077007293701,
                3887.6962890625
            ],
            "ypr": [
                -36.99994659423828,
                0.0,
                0.0
            ]
        },
        {
            "name": "Land_Tisy_Barracks",
            "pos": [
                13057.1884765625,
                10.309324264526368,
                3825.793212890625
            ],
            "ypr": [
                -33.99996566772461,
                0.0,
                0.0
            ]
        },
        {
            "name": "Land_Mil_Barracks6",
            "pos": [
                13086.173828125,
                4.678595066070557,
                3910.717041015625
            ],
            "ypr": [
                -36.99998474121094,
                0.0,
                0.0
            ]
        }
    ]
}